quattro/__init__.py
quattro/_cancelscope.py
quattro/_defer.py
quattro/_gather.py
quattro/_taskgroup.py
quattro/py.typed
quattro-25.2.0.dist-info/METADATA
quattro-25.2.0.dist-info/WHEEL
quattro-25.2.0.dist-info/licenses/LICENSE
quattro-25.2.0.dist-info/RECORD
