Metadata-Version: 2.4
Name: quattro
Version: 25.2.0
Dynamic: Summary
Author-email: Tin Tvrtkovic <tinchester@gmail.com>
License-File: LICENSE
Classifier: Intended Audience :: Developers
Classifier: License :: OSI Approved :: Apache Software License
Classifier: Programming Language :: Python :: 3.9
Classifier: Programming Language :: Python :: 3.10
Classifier: Programming Language :: Python :: 3.11
Classifier: Programming Language :: Python :: 3.12
Classifier: Programming Language :: Python :: 3.13
Classifier: Programming Language :: Python :: Implementation :: CPython
Classifier: Programming Language :: Python :: Implementation :: PyPy
Classifier: Typing :: Typed
Requires-Python: >=3.9
Requires-Dist: attrs
Requires-Dist: exceptiongroup; python_version < '3.11'
Requires-Dist: taskgroup; python_version < '3.11'
Requires-Dist: typing-extensions; python_version < '3.11'
